MANIFEST.in
README.rst
setup.py
django_klisha.egg-info/PKG-INFO
django_klisha.egg-info/SOURCES.txt
django_klisha.egg-info/dependency_links.txt
django_klisha.egg-info/not-zip-safe
django_klisha.egg-info/requires.txt
django_klisha.egg-info/top_level.txt
klisha/__init__.py
klisha/admin.py
klisha/context_processors.py
klisha/feeds.py
klisha/managers.py
klisha/models.py
klisha/settings.py
klisha/urls.py
klisha/views.py
klisha/migrations/0001_initial.py
klisha/migrations/__init__.py
klisha/static/.gitignore
klisha/static/klisha/css/bootstrap-2.3.1.min.css
klisha/static/klisha/css/klisha.css
klisha/static/klisha/fonts/sourcesanspro-light.woff
klisha/static/klisha/fonts/sourcesanspro-semibold.woff
klisha/static/klisha/js/bootstrap-2.3.1.min.js
klisha/static/klisha/js/jquery-2.0.0.min.js
klisha/templates/404.html
klisha/templates/500.html
klisha/templates/base.html
klisha/templates/klisha/archive_list.html
klisha/templates/klisha/base.html
klisha/templates/klisha/category_detail.html
klisha/templates/klisha/category_list.html
klisha/templates/klisha/picture_detail.html
klisha/templates/klisha/picture_list.html
klisha/templates/klisha/popular_list.html
klisha/templates/klisha/tag_detail.html
klisha/templates/klisha/tag_list.html
klisha/templates/klisha/include/pagination.html
klisha/templates/klisha/include/thumbnails.html
klisha/templates/klisha/templatetags/tags_cloud.html
klisha/templatetags/__init__.py
klisha/templatetags/klisha_tags.py