Metadata-Version: 1.1
Name: django-klisha
Version: 1.0.3
Summary: A standards-compliant and responsive photoblog web application, written in Python and Django
Home-page: https://github.com/zenzire/django-klisha
Author: Marcin Mierzejewski
Author-email: info@zenzire.com
License: BSD
Keywords: django,blog,photoblog,weblog,post,news,responsive
Platform: OS Independent
Classifier: Framework :: Django
Classifier: Development Status :: 5 - Production/Stable
Classifier: Environment :: Web Environment
Classifier: Programming Language :: Python
Classifier: Programming Language :: Python :: 3
Classifier: Intended Audience :: Developers
Classifier: Operating System :: OS Independent
Classifier: License :: OSI Approved :: BSD License
Classifier: Topic :: Software Development :: Libraries :: Python Modules
